scipy_doctest/__init__.py
scipy_doctest/__main__.py
scipy_doctest/conftest.py
scipy_doctest/frontend.py
scipy_doctest/impl.py
scipy_doctest/plugin.py
scipy_doctest/util.py
scipy_doctest/tests/__init__.py
scipy_doctest/tests/failure_cases.py
scipy_doctest/tests/failure_cases_2.py
scipy_doctest/tests/finder_cases.py
scipy_doctest/tests/finder_cases_2.py
scipy_doctest/tests/local_file.txt
scipy_doctest/tests/local_file_cases.py
scipy_doctest/tests/module_cases.py
scipy_doctest/tests/octave_a.mat
scipy_doctest/tests/scipy_ndimage_tutorial_clone.rst
scipy_doctest/tests/stopwords_cases.py
scipy_doctest/tests/test_finder.py
scipy_doctest/tests/test_parser.py
scipy_doctest/tests/test_pytest_configuration.py
scipy_doctest/tests/test_runner.py
scipy_doctest/tests/test_skipmarkers.py
scipy_doctest/tests/test_testfile.py
scipy_doctest/tests/test_testmod.py
scipy_doctest-2.0.1.dist-info/entry_points.txt
scipy_doctest-2.0.1.dist-info/licenses/LICENSE
scipy_doctest-2.0.1.dist-info/WHEEL
scipy_doctest-2.0.1.dist-info/METADATA
scipy_doctest-2.0.1.dist-info/RECORD
