Metadata-Version: 2.4
Name: scipy_doctest
Version: 2.0.1
Summary: Configurable, whitespace-insensitive, floating-point-aware doctest helpers.
Maintainer-email: SciPy developers <scipy-dev@python.org>
Requires-Python: >=3.8
Classifier: Development Status :: 4 - Beta
Classifier: License :: OSI Approved :: BSD License
Classifier: Intended Audience :: Developers
Classifier: Programming Language :: Python :: 3
Classifier: Framework :: Pytest
License-File: LICENSE
Requires-Dist: numpy>=1.19.5
Requires-Dist: pytest
Requires-Dist: furo==2024.8.6 ; extra == "doc"
Requires-Dist: myst-parser==4.0.0 ; extra == "doc"
Requires-Dist: sphinx==8.1.3 ; extra == "doc"
Requires-Dist: sphinx-copybutton==0.5.2 ; extra == "doc"
Requires-Dist: scipy ; extra == "test"
Requires-Dist: matplotlib ; extra == "test"
Project-URL: Home, https://github.com/scipy/scipy_doctest
Provides-Extra: doc
Provides-Extra: test
